{"$schema":"../schemas/example.schema.json","name":"empty-state-compact-break","variants":{"html":{"files":[{"target":"html/empty-state-compact-break.html","source":"html-examples/src/preview-examples/empty-state-compact-break.html"}],"dependencies":[{"name":"@siemens/ix","version":"^4.0.0"},{"name":"@siemens/ix-icons","version":"^3.3.0"}]},"react":{"files":[{"target":"react/empty-state-compact-break.tsx","source":"react-examples/src/preview-examples/empty-state-compact-break.tsx"}],"dependencies":[{"name":"@siemens/ix","version":"^4.0.0"},{"name":"@siemens/ix-icons","version":"^3.3.0"},{"name":"@siemens/ix-react","version":"^4.0.0"}]},"angular":{"files":[{"target":"angular/empty-state-compact-break.ts","source":"angular-examples/src/preview-examples/empty-state-compact-break.ts"}],"dependencies":[{"name":"@siemens/ix","version":"^4.0.0"},{"name":"@siemens/ix-icons","version":"^3.3.0"},{"name":"@siemens/ix-angular","version":"^4.0.0"}]},"angular-standalone":{"files":[{"target":"angular-standalone/empty-state-compact-break.ts","source":"angular-standalone-examples/src/preview-examples/empty-state-compact-break.ts"}],"dependencies":[{"name":"@siemens/ix","version":"^4.0.0"},{"name":"@siemens/ix-icons","version":"^3.3.0"},{"name":"@siemens/ix-angular","version":"^4.0.0"}]},"vue":{"files":[{"target":"vue/empty-state-compact-break.vue","source":"vue-examples/src/preview-examples/empty-state-compact-break.vue"}],"dependencies":[{"name":"@siemens/ix","version":"^4.0.0"},{"name":"@siemens/ix-icons","version":"^3.3.0"},{"name":"@siemens/ix-vue","version":"^4.0.0"}]}}}